orwynn/__init__.py
orwynn/_cfg.py
orwynn/env.py
sb_orwynn-3.1.0.dist-info/license
sb_orwynn-3.1.0.dist-info/METADATA
sb_orwynn-3.1.0.dist-info/WHEEL
sb_orwynn-3.1.0.dist-info/RECORD
